blackspammerbd/__init__.py
blackspammerbd/core.py
blackspammerbd1/__init__.py
blackspammerbd1/main.py
blackspammerbd1/server.py
blackspammerbd1-1.0.dist-info/LICENSE.chromedriver
blackspammerbd1-1.0.dist-info/METADATA
blackspammerbd1-1.0.dist-info/WHEEL
blackspammerbd1-1.0.dist-info/entry_points.txt
blackspammerbd1-1.0.dist-info/top_level.txt
blackspammerbd1-1.0.dist-info/RECORD
